autora/experiment_runner/experimentation_manager/firebase/__init__.py
autora_experiment_runner_experimentation_manager_firebase-1.1.5.dist-info/licenses/LICENSE
autora_experiment_runner_experimentation_manager_firebase-1.1.5.dist-info/METADATA
autora_experiment_runner_experimentation_manager_firebase-1.1.5.dist-info/WHEEL
autora_experiment_runner_experimentation_manager_firebase-1.1.5.dist-info/top_level.txt
autora_experiment_runner_experimentation_manager_firebase-1.1.5.dist-info/RECORD
