Metadata-Version: 2.4
Name: autora-experiment-runner-experimentation-manager-firebase
Version: 1.1.5
Summary: AutoRA Experimentation Manager Firebase provides functionality to manage communication of conditions and observations between AutoRA and an experiment on Firebase.
Author-email: Younes Strittmatter <younes_strittmatter@brown.edu>
License: MIT License
Project-URL: homepage, http://www.empiricalresearch.ai
Project-URL: repository, https://github.com/AutoResearch/autora-experiment-runner-experimentation-manager-firebase
Project-URL: documentation, https://autoresearch.github.io/autora/
Requires-Python: <4,>=3.8
License-File: LICENSE
Requires-Dist: autora-core
Requires-Dist: firebase-admin
Requires-Dist: numpy
Provides-Extra: dev
Requires-Dist: autora-core[dev]; extra == "dev"
Dynamic: license-file
